LICENSE
MANIFEST.in
README.txt
setup.py
bennu/__init__.py
bennu/emailutility.py
bennu/externaldb.py
bennu/filesystemutility.py
bennu/launcher.py
bennu/localdb.py
bennu.egg-info/PKG-INFO
bennu.egg-info/SOURCES.txt
bennu.egg-info/dependency_links.txt
bennu.egg-info/entry_points.txt
bennu.egg-info/requires.txt
bennu.egg-info/top_level.txt
bennu/api/__init__.py
bennu/api/apis.py
bennu/api/flaskrunner.py
bennu/api/spiderForYahooCurrency.py
bennu/mod/__init__.py
bennu/ui/__init__.py
bennu_res/__init__.py
bennu_res/__init__.pyc
bennu_res/chromedriver.exe
bennu_res/icon.ico
bennu_res/phantomjs
bennu_res/phantomjs.exe
bennu_res/__pycache__/__init__.cpython-34.pyc